{"is_source_file": false, "format": "", "description": "", "external_files": [], "external_methods": [], "published": [], "classes": [], "methods": [], "calls": [], "search-terms": [], "state": 2, "file_id": 11, "knowledge_revision": 44, "git_revision": "8852a9631a15621e3574a665cf016fca1f573ec8", "hash": "a15a955b03e13d34dd1907ae7299ddfb", "format-version": 4, "code-base-name": "frontend_games_ui", "filename": "frontend_games_ui/README.md", "revision_history": [{"44": "8852a9631a15621e3574a665cf016fca1f573ec8"}]}